yacare_cluster/__init__.py
yacare_cluster/yacare.py
yacare_cluster-0.2.dist-info/licenses/LICENSE
yacare_cluster-0.2.dist-info/METADATA
yacare_cluster-0.2.dist-info/WHEEL
yacare_cluster-0.2.dist-info/top_level.txt
yacare_cluster-0.2.dist-info/RECORD
