Metadata-Version: 2.4
Name: yacare_cluster
Version: 0.2
Summary: Package to use the YACARE algorithm for clustering data
Author-email: Nicolas Chéron <nicolas.cheron@ens.psl.eu>
License-Expression: GPL-3.0-only
Project-URL: Homepage, https://github.com/ncheron/yacare
Project-URL: Issues, https://github.com/ncheron/yacare/issues
Classifier: Programming Language :: Python :: 3
Classifier: Operating System :: OS Independent
Requires-Python: >=3.8
License-File: LICENSE
Dynamic: license-file
